odoo/addons/l10n_cl_sii_reference/README.rst
odoo/addons/l10n_cl_sii_reference/__init__.py
odoo/addons/l10n_cl_sii_reference/__manifest__.py
odoo/addons/l10n_cl_sii_reference/data/sii.concept.type.csv
odoo/addons/l10n_cl_sii_reference/data/sii.document.class.csv
odoo/addons/l10n_cl_sii_reference/data/sii.document.letter.csv
odoo/addons/l10n_cl_sii_reference/data/sii.document.type.csv
odoo/addons/l10n_cl_sii_reference/data/sii.responsibility.csv
odoo/addons/l10n_cl_sii_reference/i18n/es_CL.po
odoo/addons/l10n_cl_sii_reference/i18n/l10n_cl_sii_reference.pot
odoo/addons/l10n_cl_sii_reference/models/__init__.py
odoo/addons/l10n_cl_sii_reference/models/sii_concept_type.py
odoo/addons/l10n_cl_sii_reference/models/sii_document_class.py
odoo/addons/l10n_cl_sii_reference/models/sii_document_letter.py
odoo/addons/l10n_cl_sii_reference/models/sii_document_type.py
odoo/addons/l10n_cl_sii_reference/models/sii_optional_type.py
odoo/addons/l10n_cl_sii_reference/models/sii_reference.py
odoo/addons/l10n_cl_sii_reference/models/sii_responsibility.py
odoo/addons/l10n_cl_sii_reference/readme/CONTRIBUTORS.rst
odoo/addons/l10n_cl_sii_reference/readme/DESCRIPTION.rst
odoo/addons/l10n_cl_sii_reference/readme/USAGE.rst
odoo/addons/l10n_cl_sii_reference/security/ir.model.access.csv
odoo/addons/l10n_cl_sii_reference/static/description/icon.png
odoo/addons/l10n_cl_sii_reference/static/description/index.html
odoo/addons/l10n_cl_sii_reference/views/menuitem.xml
odoo/addons/l10n_cl_sii_reference/views/sii_concept_type.xml
odoo/addons/l10n_cl_sii_reference/views/sii_document_class.xml
odoo/addons/l10n_cl_sii_reference/views/sii_document_letter.xml
odoo/addons/l10n_cl_sii_reference/views/sii_document_type.xml
odoo/addons/l10n_cl_sii_reference/views/sii_optional_type.xml
odoo/addons/l10n_cl_sii_reference/views/sii_reference.xml
odoo/addons/l10n_cl_sii_reference/views/sii_responsibility.xml
odoo12_addon_l10n_cl_sii_reference-12.0.1.0.0.99.dev12.dist-info/METADATA
odoo12_addon_l10n_cl_sii_reference-12.0.1.0.0.99.dev12.dist-info/WHEEL
odoo12_addon_l10n_cl_sii_reference-12.0.1.0.0.99.dev12.dist-info/top_level.txt
odoo12_addon_l10n_cl_sii_reference-12.0.1.0.0.99.dev12.dist-info/RECORD
