Metadata-Version: 2.1
Name: odoo12-addon-l10n-cl-sii-reference
Version: 12.0.1.0.0.99.dev12
Summary: Store document references using SII nomenclature
Home-page: https://github.com/OCA/l10n-chile
Author: Daniel Santibáñez Polanco, Cooperativa OdooCoop, Konos, Open Source Integrators, Odoo Community Association (OCA)
Author-email: support@odoo-community.org
License: AGPL-3
Platform: UNKNOWN
Classifier: Programming Language :: Python
Classifier: Framework :: Odoo
Classifier: Framework :: Odoo :: 12.0
Classifier: License :: OSI Approved :: GNU Affero General Public License v3
Classifier: Development Status :: 4 - Beta
Requires-Python: >=3.5
Requires-Dist: odoo12-addon-l10n-cl-sii
Requires-Dist: odoo <12.1dev,>=12.0a
